ccd2md/CCD2MD.cif
ccd2md/FuncConv.py
ccd2md/__init__.py
ccd2md/at2ccd.py
ccd2md/at2cg.py
ccd2md/at2mem.py
ccd2md/ccd2at.py
ccd2md/ccd2cg.py
ccd2md/martini_new_lipidome.itp
ccd2md/martini_v3.itp
ccd2md/pos2cif.py
ccd2md/MemPrO/Insane4MemPrO.py
ccd2md/MemPrO/Insane4MemPrO_new_lipidome.py
ccd2md/Ref_data/17F_CCD.txt
ccd2md/Ref_data/46E_CCD.txt
ccd2md/Ref_data/5TR_CCD.txt
ccd2md/Ref_data/6OU_CCD.txt
ccd2md/Ref_data/BDDM.txt
ccd2md/Ref_data/BDDM_CHARMM.txt
ccd2md/Ref_data/BDDM_user.txt
ccd2md/Ref_data/BLMN.txt
ccd2md/Ref_data/BLMN_CHARMM.txt
ccd2md/Ref_data/BLMN_user.txt
ccd2md/Ref_data/BOG1.txt
ccd2md/Ref_data/BOG1_CHARMM.txt
ccd2md/Ref_data/BOG1_user.txt
ccd2md/Ref_data/BOG_CCD.txt
ccd2md/Ref_data/CARD.pdb
ccd2md/Ref_data/CARD_CG.txt
ccd2md/Ref_data/CARD_CHARMM.txt
ccd2md/Ref_data/CARD_user.txt
ccd2md/Ref_data/CHL1.txt
ccd2md/Ref_data/CHL1_CG.txt
ccd2md/Ref_data/CHL1_CHARMM.txt
ccd2md/Ref_data/CHL1_user.txt
ccd2md/Ref_data/CLR_CCD.txt
ccd2md/Ref_data/CYSD_CG.txt
ccd2md/Ref_data/CYSD_CHARMM.txt
ccd2md/Ref_data/CYSD_user.txt
ccd2md/Ref_data/CYSF_CG.txt
ccd2md/Ref_data/CYSF_CHARMM.txt
ccd2md/Ref_data/CYSF_user.txt
ccd2md/Ref_data/CYSG_CG.txt
ccd2md/Ref_data/CYSG_CHARMM.txt
ccd2md/Ref_data/CYSG_user.txt
ccd2md/Ref_data/CYSP.txt
ccd2md/Ref_data/CYSP_CG.txt
ccd2md/Ref_data/CYSP_CHARMM.txt
ccd2md/Ref_data/CYSP_user.txt
ccd2md/Ref_data/CYST_CG.txt
ccd2md/Ref_data/CYST_CHARMM.txt
ccd2md/Ref_data/CYST_user.txt
ccd2md/Ref_data/D21_CCD.txt
ccd2md/Ref_data/D39_CCD.txt
ccd2md/Ref_data/DGPC_CG.txt
ccd2md/Ref_data/DGPC_CHARMM.txt
ccd2md/Ref_data/DGPC_user.txt
ccd2md/Ref_data/DGPE_CG.txt
ccd2md/Ref_data/DGPE_CHARMM.txt
ccd2md/Ref_data/DGPE_user.txt
ccd2md/Ref_data/DLPC_CG.txt
ccd2md/Ref_data/DLPC_CHARMM.txt
ccd2md/Ref_data/DLPC_user.txt
ccd2md/Ref_data/DLPE.txt
ccd2md/Ref_data/DLPE_CG.txt
ccd2md/Ref_data/DLPE_CHARMM.txt
ccd2md/Ref_data/DLPE_user.txt
ccd2md/Ref_data/DMPC.txt
ccd2md/Ref_data/DMPC_CG.txt
ccd2md/Ref_data/DMPC_CHARMM.txt
ccd2md/Ref_data/DMPC_user.txt
ccd2md-1.0.3.dist-info/licenses/LICENSE
ccd2md-1.0.3.dist-info/METADATA
ccd2md-1.0.3.dist-info/WHEEL
ccd2md-1.0.3.dist-info/entry_points.txt
ccd2md-1.0.3.dist-info/top_level.txt
ccd2md-1.0.3.dist-info/RECORD
