Metadata-Version: 2.4
Name: ccd2md
Version: 1.0.3
Summary: A suite of packages for the conversion of co-folding outputs into simulatable PDB files.
Author: Matyas Parrag
Author-email: "Katarina E. Blow" <katarina.blow@warwick.ac.uk>, "Phillip J. Stansfeld" <phillip.stansfeld@warwick.ac.uk>
Maintainer-email: "Katarina E. Blow" <katarina.blow@warwick.ac.uk>, "Phillip J. Stansfeld" <phillip.stansfeld@warwick.ac.uk>
License-Expression: GPL-3.0
Project-URL: Homepage, https://github.com/keb721/CCD2MD
Project-URL: Issues, https://github.com/keb721/CCD2MD/issues
Classifier: Programming Language :: Python :: 3
Requires-Python: >=3.11
License-File: LICENSE
Requires-Dist: numpy>=1.26.4
Requires-Dist: pandas>=2.3.1
Provides-Extra: all
Requires-Dist: vermouth>=0.13.0; extra == "all"
Requires-Dist: memprod==0.0.9; extra == "all"
Requires-Dist: cg2at-lite==0.2.3; extra == "all"
Dynamic: license-file
